nubix_outlook/__init__.py
nubix_outlook/outlook_mailbox.py
nubix_outlook-1.0.0.dist-info/METADATA
nubix_outlook-1.0.0.dist-info/WHEEL
nubix_outlook-1.0.0.dist-info/RECORD
