Metadata-Version: 2.4
Name: nubix-outlook
Version: 1.0.0
Summary: Outlook mailbox client built on Microsoft Graph with helpers for attachment processing.
Project-URL: Repository, https://git.nubix.online/python/ai.git
Author-email: Nubix <l.laarveld@nubix.nl>
License: MIT
Classifier: Development Status :: 4 - Beta
Classifier: Intended Audience :: Developers
Classifier: License :: OSI Approved :: MIT License
Classifier: Programming Language :: Python :: 3
Classifier: Programming Language :: Python :: 3.11
Classifier: Programming Language :: Python :: 3.12
Classifier: Programming Language :: Python :: 3.13
Requires-Python: >=3.11
Requires-Dist: msal>=1.30.0
Requires-Dist: requests>=2.32.5
